ge25519/__init__.py
ge25519/ge25519.py
ge25519-1.5.1.dist-info/LICENSE
ge25519-1.5.1.dist-info/METADATA
ge25519-1.5.1.dist-info/WHEEL
ge25519-1.5.1.dist-info/top_level.txt
ge25519-1.5.1.dist-info/RECORD
